zipfile36.py
zipfile36-0.1.2.dist-info/WHEEL
zipfile36-0.1.2.dist-info/METADATA
zipfile36-0.1.2.dist-info/RECORD
