Metadata-Version: 1.2
Name: zipfile36
Version: 0.1.2
Summary: Read and write ZIP files - backport of the zipfile module from Python 3.6
Home-page: https://gitlab.com/takluyver/zipfile36
License: UNKNOWN
Author: Thomas Kluyver
Author-email: thomas@kluyver.me.uk
Classifier: License :: OSI Approved :: Python Software Foundation License
Classifier: Programming Language :: Python :: 3
Classifier: Topic :: System :: Archiving :: Compression
